pyNetia/__init__.py
pyNetia-0.1.3.dist-info/LICENSE
pyNetia-0.1.3.dist-info/METADATA
pyNetia-0.1.3.dist-info/WHEEL
pyNetia-0.1.3.dist-info/top_level.txt
pyNetia-0.1.3.dist-info/RECORD
