Metadata-Version: 2.1
Name: pyNetia
Version: 0.1.3
Summary: Python wrapper for Netia Player
Home-page: https://github.com/korasinski/pyNetia
Author: Jakub Orasiński
Author-email: korasinski@icloud.com
License: gpl-3.0
Keywords: Netia Player,Home Assistant,custom component
Platform: UNKNOWN
Classifier: Development Status :: 4 - Beta
Classifier: License :: OSI Approved :: GNU General Public License v3 (GPLv3)
Classifier: Programming Language :: Python
Classifier: Operating System :: OS Independent
Requires-Dist: requests
